setup.cfg
setup.py
pyparadox_alarm/__init__.py
pyparadox_alarm/alarm_panel.py
pyparadox_alarm/alarm_serial_comms.py
pyparadox_alarm/alarm_state.py
pyparadox_alarm/paradox_defaults.py
pyparadox_alarm.egg-info/PKG-INFO
pyparadox_alarm.egg-info/SOURCES.txt
pyparadox_alarm.egg-info/dependency_links.txt
pyparadox_alarm.egg-info/requires.txt
pyparadox_alarm.egg-info/top_level.txt