Metadata-Version: 1.1
Name: pyparadox-alarm
Version: 1.0.0
Summary: A python3 library for running asynchronous communications with Paradox alarm control panel modules.
Home-page: https://github.com/PollieKrismis/pyparadox_alarm.git
Author: Paul Burger
Author-email: PollieXmas@icloud.com
License: MIT
Platform: UNKNOWN
Classifier: Development Status :: 4 - Beta
Classifier: Programming Language :: Python :: 3.4
Classifier: Programming Language :: Python :: 3.5
